custom_prompts/__init__.py
smartygpt/__init__.py
smartygpt/contexts.py
smartygpt/models.py
smartygpt/smartygpt.py
smarty_gpt-2.0.0.dist-info/LICENSE
smarty_gpt-2.0.0.dist-info/METADATA
smarty_gpt-2.0.0.dist-info/WHEEL
smarty_gpt-2.0.0.dist-info/top_level.txt
smarty_gpt-2.0.0.dist-info/RECORD
